arabic_phonetiser/__init__.py
arabic_phonetiser/phonetise_buckwalter.py
arabic_phonetiser/symbols.py
tests/__init__.py
arabic_phonetiser-1.0.5.dist-info/LICENSE.md
arabic_phonetiser-1.0.5.dist-info/METADATA
arabic_phonetiser-1.0.5.dist-info/WHEEL
arabic_phonetiser-1.0.5.dist-info/top_level.txt
arabic_phonetiser-1.0.5.dist-info/RECORD
