Metadata-Version: 2.1
Name: arabic-phonetiser
Version: 1.0.5
Home-page: https://github.com/hayderkharrufa/arabic-phonetiser
Author: Hayder Kharrufa
Author-email: 
License: Creative Commons Attribution-NonCommercial 4.0 International License
License-File: LICENSE.md
Requires-Dist: arabic-buckwalter-transliteration
